pypi_verify_now.py
pypi_verify_now-0.6.dist-info/licenses/LICENSE
pypi_verify_now-0.6.dist-info/METADATA
pypi_verify_now-0.6.dist-info/WHEEL
pypi_verify_now-0.6.dist-info/entry_points.txt
pypi_verify_now-0.6.dist-info/top_level.txt
pypi_verify_now-0.6.dist-info/RECORD
