Metadata-Version: 2.4
Name: pypi-verify-now
Version: 0.6
Summary: Verifies pypi-attestations in a build pipeline
Author-email: Joost Molenaar <jjm@j0057.nl>
License-Expression: MIT
Project-URL: repository, https://gitlab.com/j0057-git/python/pypi-verify-now
Project-URL: issues, https://gitlab.com/j0057-git/python/pypi-verify-now/-/issues
Keywords: sigstore
Classifier: Programming Language :: Python :: 3
Classifier: Programming Language :: Python :: 3 :: Only
Classifier: Programming Language :: Python :: Implementation :: CPython
Requires-Python: >=3.9
License-File: LICENSE
Requires-Dist: pip~=25.2
Requires-Dist: pypi-attestations~=0.0
Dynamic: license-file
